AUTHORS.rst
HISTORY.rst
LICENSE
MANIFEST.in
README.rst
setup.cfg
setup.py
soif/__init__.py
soif/_version.py
soif/core.py
soif/oidata.py
soif/oidataempty.py
soif/oiexception.py
soif/oifiting.py
soif/oifits.py
soif/oigrab.py
soif/oiload.py
soif/oimainobject.py
soif/oimodel.py
soif/oipriors.py
soif/oiunitmodels.py
soif.egg-info/PKG-INFO
soif.egg-info/SOURCES.txt
soif.egg-info/dependency_links.txt
soif.egg-info/requires.txt
soif.egg-info/top_level.txt